renamewheel/__init__.py
renamewheel/main.py
renamewheel-0.4.1.dist-info/licenses/LICENSE
renamewheel-0.4.1.dist-info/METADATA
renamewheel-0.4.1.dist-info/WHEEL
renamewheel-0.4.1.dist-info/entry_points.txt
renamewheel-0.4.1.dist-info/top_level.txt
renamewheel-0.4.1.dist-info/RECORD
