Metadata-Version: 2.4
Name: renamewheel
Version: 0.4.1
Summary: Script for renaming Linux wheels.
Author-email: Hugh Sorby <h.sorby@auckland.ac.nz>
License-Expression: Apache-2.0
Project-URL: Homepage, https://raw.githubusercontent.com/hsorby/renamewheel/refs/heads/main/README.rst
Project-URL: Repository, https://github.com/hsorby/renamewheel
Keywords: Rename,Wheel
Classifier: Programming Language :: Python :: 3
Classifier: Operating System :: OS Independent
Classifier: Topic :: Scientific/Engineering :: Medical Science Apps.
Requires-Python: >=3.8
License-File: LICENSE
Requires-Dist: auditwheel>=6.4
Provides-Extra: test
Requires-Dist: coverage; extra == "test"
Dynamic: license-file
